mpitree/__init__.py
mpitree/base_estimator.py
mpitree/decision_tree.py
mpitree-0.0.8.dist-info/LICENSE
mpitree-0.0.8.dist-info/METADATA
mpitree-0.0.8.dist-info/WHEEL
mpitree-0.0.8.dist-info/top_level.txt
mpitree-0.0.8.dist-info/RECORD
