Metadata-Version: 2.1
Name: mpitree
Version: 0.0.8
Summary: A Parallel Decision Tree Implementation using MPI
Home-page: https://github.com/duong-jason/mpitree
Author: Jason Duong
Author-email: my.toe.ben@gmail.com
License: MIT
Classifier: Programming Language :: Python :: 3
Classifier: License :: OSI Approved :: MIT License
Classifier: Operating System :: OS Independent
Requires-Python: >=3.10
License-File: LICENSE
Requires-Dist: matplotlib
Requires-Dist: mpi4py
Requires-Dist: numpy
Requires-Dist: pandas
Requires-Dist: scikit-learn
Provides-Extra: testing
Requires-Dist: black ; extra == 'testing'
Requires-Dist: pytest ; extra == 'testing'
Requires-Dist: pylint ; extra == 'testing'
Requires-Dist: numpydoc ; extra == 'testing'
